{"yZYQpge1W5s": ["aMcjxSThD54", "ly67lnekEwc", "IRCZ1Mt2a8M", "2v8lq_vnklI", "7QRQjrsFnR4", "SiijS_9hPkM", "euC3kmns6l4", "Xmyud5O54Ds", "N2lLPBiD_d0", "K5f4fUDZU7o", "WEP5ubPMGDU", "2mTS57hkAUk", "UZMIbo_DxJk", "dvBbxbjFRw4", "tYrdMjVXyNg", "0EOkC44ZIfo", "TmNSlF7lcaw", "_iudkPi4_sY", "yrwSOMFZvHY", "Iy4vq8RdPGU"], "tYrdMjVXyNg": ["_El9riy9Zjw", "-1NFirxhXWE", "aMcjxSThD54", "0cn3VBjfN8g", "he-7vs0BkLE", "Tt-ywOVbOiQ", "k7aQEqDbuf8", "TmNSlF7lcaw", "JN3KPFbWCy8", "kD5yc1LQrpQ", "G1p6rlDCxq0", "DxL2HoqLbyA", "4AWLcxTGZPA", "1X_KdkoGxSs", "9NsbsLV6hX4", "jvqFAi7vkBc", "CKJuC5CUMgU", "QGLvwQX-Aos", "AF8DOS4C2KM", "8oRRZiRQxTs"], "bEh0Q94Gjss": ["JXHgc073nIs", "bpAi70WWBlw", "K0OtGIPRcAs", "M7TNP2OTY2g", "otCYl7_uU8Y", "IakAyNtrE_E", "Rd8J-9uUnfc", "aZ5EsdnpLMI", "R_J_T7TWbXY", "rAcEcb2osi4", "ZGHHE0M3080", "1lVM5zXKmFo", "c7tgsUv3UlU", "uiUPD-z9DTg", "lLWbcRZxYu0", "NSNQibwWGvU", "Qk2KqsWkT5g", "6TqhcZsxrPA", "a_-BrHqQwXI", "cZlsZwcIgpc"], "6BsXLnLn9ok": ["YNQPQkV3nhw", "J-AzuFj1iS4", "rFxu7NEoKC8", "LFMuLqZ1zaU", "6Vc2bM2aQsw", "d16LNHIEJzs", "LLpte98_jR4", "4dFvHicFoRI", "vcCBacPWLrc", "9hdT8PgT19w", "71ZyO437w4c", "ASAsHdwFAa4", "1UnIDL-eHOs", "1Jj-sJ78O6M", "vb11oOHYNXM", "zNlm1eFjArU", "KaGSYGhUkvM", "7ziWrneMYss", "jdYwMLSNHnU", "Nq50PGFX5dk"], "Qe5WT22-AO8": ["Zrv1EDIqHkY", "nfDoml-Db64", "QQkmJI63ykI", "8DBhTXM_Br4", "AF8d72mA41M", "ett_8wLJ87U", "2VQDqzT4SOM", "6DHgkMYgp7w", "tib0lgpjbu8", "9yjZpBq1XBE", "mT6QhV9Qyzw", "mAh4IJysiLU", "BRSkRlPa5_E", "CKJuC5CUMgU", "YGfF2TAkpJ4", "Riio1eKOSKg", "7rIJNT7dCmE", "I6xwMIUPHss", "8VIdedVr0sE", "TfIQNTZIktw"], "home": []}