{"yZYQpge1W5s": ["aMcjxSThD54", "TmNSlF7lcaw", "WEP5ubPMGDU", "7QRQjrsFnR4", "oaDTiWaYfcM", "ly67lnekEwc", "AscPHmLWo-M", "kasiov0ytEc", "di2FM8WZI5E", "zN2_0WC7UfU", "2v8lq_vnklI", "t3xInUaRVhY", "IRCZ1Mt2a8M", "_iudkPi4_sY", "UZMIbo_DxJk", "AhZLh_sApPo", "dvBbxbjFRw4", "euC3kmns6l4", "eYK7CxcaZw4", "nS9W-wlJHPA"], "tYrdMjVXyNg": ["_El9riy9Zjw", "aMcjxSThD54", "oaDTiWaYfcM", "-1NFirxhXWE", "AF8DOS4C2KM", "TfIQNTZIktw", "odmOcs6tYfU", "zN2_0WC7UfU", "f_lRdkH_QoY", "TmNSlF7lcaw", "ZNtzLsd6Xnc", "t4qv7hSysyw", "JN3KPFbWCy8", "mScpHTIi-kM", "k7aQEqDbuf8", "7qShHd-uxKQ", "8oRRZiRQxTs", "eYK7CxcaZw4", "he-7vs0BkLE", "CKJuC5CUMgU"], "bEh0Q94Gjss": ["53a0Y2xPrTQ", "hnoMsftQPY8", "ZGHHE0M3080", "G8rUIUXUXqI", "3JKWmWAlMD4", "K0OtGIPRcAs", "5kHcLil3G7Y", "ccMr0OhhuIw", "bpAi70WWBlw", "rAcEcb2osi4", "xecEV4dSAXE", "oue5A-7Hpx4", "bqOOrFFkKeo", "dbwHnkaUVC0", "fq6jDxJk1LM", "A_8BDrO2Dlk", "Ez90rXhMWjE", "b6pdFXcC1bU", "oaDTiWaYfcM", "SaCg7t9sMZg"], "6BsXLnLn9ok": ["YNQPQkV3nhw", "J-AzuFj1iS4", "rFxu7NEoKC8", "LFMuLqZ1zaU", "6Vc2bM2aQsw", "AlFnPAydJgk", "-ex7f7KVl3I", "ZNtzLsd6Xnc", "1UnIDL-eHOs", "xYqhyR8MR_w", "7OeeHz0uNdM", "9hdT8PgT19w", "zNlm1eFjArU", "KaGSYGhUkvM", "54H8ppxnp8I", "hJn8iUe6rwY", "yY96hTb8WgI", "s8VOM8ET1WU", "XGuxJNozisM", "jdYwMLSNHnU"], "Qe5WT22-AO8": ["st6yupvNkVo", "Y44fyh4ap7k", "Zrv1EDIqHkY", "nfDoml-Db64", "QQkmJI63ykI", "8DBhTXM_Br4", "oaDTiWaYfcM", "AF8d72mA41M", "CKJuC5CUMgU", "ett_8wLJ87U", "zN2_0WC7UfU", "eYK7CxcaZw4", "flXrLGPY3SU", "2VQDqzT4SOM", "TfIQNTZIktw", "Xzv84ZdtlE0", "BRSkRlPa5_E", "dPWYUELwIdM", "3xSUwgg1L4g", "I6xwMIUPHss"], "home": ["LqME1y6Mlyg", "8S_p04uRZLE", "Scwsg9Ai3rg", "KchX52bIZSg", "BFEEgfJoqjg", "IRiHBs62jfE", "Nns3DQYBryA", "vTF-Kz_7L0c", "tbFUK3r8GGU", "RG2IK8oRZNA", "WCli0gyNwL0", "aaodJqJ2o60", "LxyyvW_fcqw", "CGi5W-gG-vs", "bSpOU-5aq-8", "IyiArdfb_gA", "VVkVrSMQGSU", "fAGrM6P3IKQ", "fCurMofVoic", "lNe1D_E3R8E", "lPAzMw8hwhg", "Beo-4JJytaA"]}